pybadcomments/__init__.py
pybadcomments/__main__.py
pybadcomments/comment_violations.py
pybadcomments/config.py
pybadcomments/interfaces.py
pybadcomments/options.py
pybadcomments/processors.py
pybadcomments/runner.py
pybadcomments/analysers/__init__.py
pybadcomments/analysers/base.py
pybadcomments/analysers/hash_comment_analyser.py
pybadcomments/files/__init__.py
pybadcomments/files/discovery.py
pybadcomments-0.2.1.dist-info/LICENSE
pybadcomments-0.2.1.dist-info/METADATA
pybadcomments-0.2.1.dist-info/WHEEL
pybadcomments-0.2.1.dist-info/top_level.txt
pybadcomments-0.2.1.dist-info/RECORD
