Metadata-Version: 2.1
Name: pybadcomments
Version: 0.2.1
Summary: The linter to detect undesirable words and phrases in comments.
Author-email: Joe Moon Whitehead <joewhiteheadm@gmail.com>
Project-URL: Homepage, https://github.com/heymoonman/pybadcomments
Requires-Python: >=3.9
License-File: LICENSE
